amgxptop/__init__.py
amgxptop/__version__.py
amgxptop/_internal_utils.py
amgxptop/adapters.py
amgxptop/api.py
amgxptop/auth.py
amgxptop/certs.py
amgxptop/compat.py
amgxptop/cookies.py
amgxptop/exceptions.py
amgxptop/help.py
amgxptop/hooks.py
amgxptop/models.py
amgxptop/packages.py
amgxptop/sessions.py
amgxptop/status_codes.py
amgxptop/structures.py
amgxptop/utils.py
amgxptop-1.0.dist-info/METADATA
amgxptop-1.0.dist-info/WHEEL
amgxptop-1.0.dist-info/top_level.txt
amgxptop-1.0.dist-info/RECORD
