Metadata-Version: 2.1
Name: amgxptop
Version: 1.0
Summary: Request Package LMAO
Author: amgxp
Author-email: <Amgxpp@gmail.com>
Keywords: requests
Classifier: Development Status :: 1 - Planning
Classifier: Intended Audience :: Developers
Classifier: Programming Language :: Python :: 3
Classifier: Operating System :: Unix
Classifier: Operating System :: MacOS :: MacOS X
Classifier: Operating System :: Microsoft :: Windows
Requires-Dist: vardxg
